ai_model_base/__init__.py
ai_model_base/model/__init__.py
ai_model_base/model/BaseModel.py
ai_model_base/resource/__init__.py
ai_model_base/resource/factory/__init__.py
ai_model_base/resource/factory/ModelFactory.py
ai_model_base/resource/pool/__init__.py
ai_model_base/resource/pool/ModelPool.py
ai_model_base/resource/proxy/__init__.py
ai_model_base/resource/proxy/DynamicProxy.py
ai_model_base-0.0.1.dev3.dist-info/METADATA
ai_model_base-0.0.1.dev3.dist-info/WHEEL
ai_model_base-0.0.1.dev3.dist-info/RECORD
