Metadata-Version: 2.1
Name: ai-model-base
Version: 0.0.1.dev3
Summary: 
Home-page: https://github.com/hackty/ai-model-base
License: MIT
Author: taoyang
Author-email: hackty@163.com
Requires-Python: >=3.10,<4.0
Classifier: License :: OSI Approved :: MIT License
Classifier: Programming Language :: Python :: 3
Classifier: Programming Language :: Python :: 3.10
Classifier: Programming Language :: Python :: 3.11
Classifier: Programming Language :: Python :: 3.12
Requires-Dist: ai-model-dispatcher (>=0.0.1.dev4,<0.0.2)
Project-URL: Repository, https://github.com/hackty/ai-model-base
